ec2_slackbot/__init__.py
ec2_slackbot/app.py
ec2_slackbot/aws_handler.py
ec2_slackbot/instance_checker.py
ec2_slackbot/slack_handler.py
ec2_slackbot/web_server.py
ec2_slackbot-0.1.26.dist-info/LICENSE
ec2_slackbot-0.1.26.dist-info/METADATA
ec2_slackbot-0.1.26.dist-info/WHEEL
ec2_slackbot-0.1.26.dist-info/entry_points.txt
ec2_slackbot-0.1.26.dist-info/RECORD
