Metadata-Version: 2.1
Name: ec2-slackbot
Version: 0.1.26
Summary: 
Author: Robert Dargavel Smith
Author-email: teticio@gmail.com
Requires-Python: >=3.10,<4.0
Classifier: Programming Language :: Python :: 3
Classifier: Programming Language :: Python :: 3.10
Classifier: Programming Language :: Python :: 3.11
Classifier: Programming Language :: Python :: 3.12
Classifier: Programming Language :: Python :: 3.13
Requires-Dist: boto3 (>=1.34.131,<2.0.0)
Requires-Dist: cryptography (>=42.0.8,<43.0.0)
Requires-Dist: flask (>=3.0.3,<4.0.0)
Requires-Dist: pyyaml (>=6.0.1,<7.0.0)
Requires-Dist: requests (>=2.32.3,<3.0.0)
Requires-Dist: slack-sdk (>=3.29.0,<4.0.0)
